graphql_extensions/__init__.py
graphql_extensions/decorators.py
graphql_extensions/exceptions.py
graphql_extensions/lookups.py
graphql_extensions/settings.py
graphql_extensions/shortcuts.py
graphql_extensions/test.py
graphql_extensions/types.py
graphql_extensions/views.py
graphql_extensions/locale/es/LC_MESSAGES/django.mo
graphql_extensions/locale/es/LC_MESSAGES/django.po
django_graphql_extensions-0.1.0.dist-info/LICENSE
django_graphql_extensions-0.1.0.dist-info/METADATA
django_graphql_extensions-0.1.0.dist-info/WHEEL
django_graphql_extensions-0.1.0.dist-info/top_level.txt
django_graphql_extensions-0.1.0.dist-info/RECORD
